tbselenium/__init__.py
tbselenium/common.py
tbselenium/exceptions.py
tbselenium/set_profile.py
tbselenium/set_profile_nops.py
tbselenium/tbbinary.py
tbselenium/tbdriver.py
tbselenium/unpack_tb.py
tbselenium/utils.py
tbselenium/test/__init__.py
tbselenium/test/conftest.py
tbselenium/test/fixtures.py
tbselenium/test/test_addons.py
tbselenium/test/test_bridge.py
tbselenium/test/test_browser.py
tbselenium/test/test_context_switch.py
tbselenium/test/test_disable_javascript.py
tbselenium/test/test_env.py
tbselenium/test/test_exceptions.py
tbselenium/test/test_screenshot.py
tbselenium/test/test_set_security_level.py
tbselenium/test/test_stem.py
tbselenium/test/test_tbdriver.py
tbselenium/test/test_tor.py
tbselenium/test/test_utils.py
tbselenium-0.6.3.dist-info/METADATA
tbselenium-0.6.3.dist-info/WHEEL
tbselenium-0.6.3.dist-info/top_level.txt
tbselenium-0.6.3.dist-info/RECORD
