Metadata-Version: 2.1
Name: tbselenium
Version: 0.6.3
Summary: Tor Browser automation with Selenium
Home-page: https://github.com/webfp/tor-browser-selenium
Author: Gunes Acar
License: UNKNOWN
Keywords: tor,selenium,tor browser
Platform: UNKNOWN
Requires-Dist: selenium (>=4)
